LICENSE
README.md
pypokedex/__init__.py
pypokedex/api.py
pypokedex/exceptions.py
pypokedex/pokemon.py
pypokedex-1.5.0.dist-info/LICENSE
pypokedex-1.5.0.dist-info/WHEEL
pypokedex-1.5.0.dist-info/METADATA
pypokedex-1.5.0.dist-info/RECORD
