Metadata-Version: 2.1
Name: pypokedex
Version: 1.5.0
Summary: A minimal pokedex library
Home-page: https://github.com/arnavb/pypokedex#readme
License: MIT
Author: Arnav Borborah
Author-email: arnavborborah11@gmail.com
Requires-Python: >=3.6,<4.0
Classifier: Development Status :: 5 - Production/Stable
Classifier: Intended Audience :: Developers
Classifier: License :: OSI Approved :: MIT License
Classifier: Natural Language :: English
Classifier: Operating System :: OS Independent
Classifier: Programming Language :: Python :: 3
Classifier: Programming Language :: Python :: 3.6
Classifier: Programming Language :: Python :: 3.7
Classifier: Programming Language :: Python :: 3.8
Classifier: Topic :: Games/Entertainment
Classifier: Topic :: Software Development :: Libraries
Requires-Dist: requests (>=2.21.0,<3.0.0)
Project-URL: Repository, https://github.com/arnavb/pypokedex
